mime_converter/__init__.py
mime_converter/mapping.py
mime_converter/utils.py
mime_converter-1.0.0.dist-info/METADATA
mime_converter-1.0.0.dist-info/WHEEL
mime_converter-1.0.0.dist-info/top_level.txt
mime_converter-1.0.0.dist-info/RECORD
