Metadata-Version: 2.4
Name: Mime_converter
Version: 1.0.0
Summary: Converts mime to file extensions
Author: Jacob D
Author-email: d8008385@gmail.com
Requires-Python: >=3.11
Dynamic: author
Dynamic: author-email
Dynamic: requires-python
Dynamic: summary
